PyMsOfa/PyMsOfa.py
PyMsOfa/PyMsOfa_astrometry.py
PyMsOfa/PyMsOfa_basic.py
PyMsOfa/PyMsOfa_earth_attitude.py
PyMsOfa/PyMsOfa_t.py
PyMsOfa/PyMsOfa_time.py
PyMsOfa/__init__.py
libsofa_c/so.cp39-win_amd64.pyd
PyMsOfa_ctpyes-0.0.1.dist-info/LICENSE
PyMsOfa_ctpyes-0.0.1.dist-info/METADATA
PyMsOfa_ctpyes-0.0.1.dist-info/WHEEL
PyMsOfa_ctpyes-0.0.1.dist-info/top_level.txt
PyMsOfa_ctpyes-0.0.1.dist-info/RECORD
